safe_security_logger/__init__.py
safe_security_logger/logger.py
safe_security_logger-1.8.0.dist-info/LICENSE.txt
safe_security_logger-1.8.0.dist-info/METADATA
safe_security_logger-1.8.0.dist-info/WHEEL
safe_security_logger-1.8.0.dist-info/top_level.txt
safe_security_logger-1.8.0.dist-info/RECORD
