Metadata-Version: 2.2
Name: safe-security-logger
Version: 1.8.0
Summary: Custom logging framework from SAFE security
Home-page: https://github.com/Safe-Security/py-logger/py-logger
Author: deepak-sreekumar
Author-email: deepak.s@safe.security
License: MIT
Project-URL: Source, https://github.com/Safe-Security/py-logger
Platform: any
Classifier: Development Status :: 4 - Beta
Classifier: Programming Language :: Python
Requires-Python: >=3.7
License-File: LICENSE.txt
Requires-Dist: importlib-metadata; python_version < "3.8"
Requires-Dist: python-json-logger>=2.0.4
Provides-Extra: testing
Requires-Dist: setuptools; extra == "testing"
Requires-Dist: pytest; extra == "testing"
Requires-Dist: pytest-cov; extra == "testing"
